pyearthtools/data/__init__.py
pyearthtools/data/catalog.py
pyearthtools/data/collection.py
pyearthtools/data/commands.py
pyearthtools/data/config.py
pyearthtools/data/data.yaml
pyearthtools/data/decorators.py
pyearthtools/data/exceptions.py
pyearthtools/data/load.py
pyearthtools/data/logger.py
pyearthtools/data/time.py
pyearthtools/data/utils.py
pyearthtools/data/warnings.py
pyearthtools/data/archive/__init__.py
pyearthtools/data/archive/extensions.py
pyearthtools/data/archive/root.py
pyearthtools/data/archive/utils.py
pyearthtools/data/archive/zarr.py
pyearthtools/data/archive/registered/NCI.yaml
pyearthtools/data/archive/registered/README.md
pyearthtools/data/archive/registered/UKMO.yaml
pyearthtools/data/archive/registered/__init__.py
pyearthtools/data/archive/registered/register.txt
pyearthtools/data/archive/registered/template.yaml
pyearthtools/data/derived/__init__.py
pyearthtools/data/derived/derived.py
pyearthtools/data/derived/insolation.py
pyearthtools/data/download/__init__.py
pyearthtools/data/download/_weatherbench.py
pyearthtools/data/download/arcoera5.py
pyearthtools/data/download/templates.py
pyearthtools/data/download/weatherbench.py
pyearthtools/data/download/cds/ERA5.py
pyearthtools/data/download/cds/_ERA5.py
pyearthtools/data/download/cds/__init__.py
pyearthtools/data/download/cds/cds.py
pyearthtools/data/download/cds/variables/ERA5.valid
pyearthtools/data/download/cds/variables/__init__.py
pyearthtools/data/download/ecmwf_opendata/__init__.py
pyearthtools/data/download/ecmwf_opendata/convenience.py
pyearthtools/data/download/ecmwf_opendata/opendata.py
pyearthtools/data/download/ecmwf_opendata/opendata.struc
pyearthtools/data/download/ecmwf_opendata/opendata_variables.py
pyearthtools/data/indexes/__init__.py
pyearthtools/data/indexes/_indexes.py
pyearthtools/data/indexes/cacheIndex.py
pyearthtools/data/indexes/combine.py
pyearthtools/data/indexes/decorators.py
pyearthtools/data/indexes/extensions.py
pyearthtools/data/indexes/fake.py
pyearthtools_data-0.5.1.dist-info/METADATA
pyearthtools_data-0.5.1.dist-info/WHEEL
pyearthtools_data-0.5.1.dist-info/entry_points.txt
pyearthtools_data-0.5.1.dist-info/licenses/LICENSE
pyearthtools_data-0.5.1.dist-info/RECORD
